dsfe/__init__.py
dsfe/optimations.py
dsfe/optimizer.py
dsfe/plotting.py
dsfe/tests/__init__.py
dsfe/tests/hgb_pcv.csv
dsfe/tests/test_optimizer.py
dsfe/tests/test_plotting.py
dsfe/tests/xy.csv
dsfe-0.1a1.dist-info/LICENSE
dsfe-0.1a1.dist-info/WHEEL
dsfe-0.1a1.dist-info/METADATA
dsfe-0.1a1.dist-info/RECORD
