Metadata-Version: 2.1
Name: dsfe
Version: 0.1a1
Summary: Data Science for Everyone
Author-email: Matthew Brett <matthew.brett@gmail.com>
Requires-Python: >=3.6
Classifier: License :: OSI Approved :: BSD License
Classifier: Programming Language :: Python :: 3
Requires-Dist: scipy
Requires-Dist: matplotlib
Project-URL: Home, https://github.com/odsti/dsfe-package
